{"orderHistory":[{"orderId":45,"orderDate":"Aug 22, 2024, 04:57:19 PM","items":[{"name":"Tiramisu","price":10.0,"available":true,"photoUrl":"http://localhost:8080/menu_item_images/restaurant2_Tiramisu.jpg","description":"Delicious Tiramisu","quantity":1},{"name":"Churros","price":11.0,"available":true,"photoUrl":"http://localhost:8080/menu_item_images/restaurant2_Churros.jpg","description":"Delicious Churros","quantity":1},{"name":"Bruschetta","price":12.0,"available":true,"photoUrl":"http://localhost:8080/menu_item_images/restaurant2_Bruschetta.jpg","description":"Delicious Bruschetta","quantity":0},{"name":"Pancakes","price":13.0,"available":true,"photoUrl":"http://localhost:8080/menu_item_images/restaurant2_Pancakes.jpg","description":"Delicious Pancakes","quantity":0},{"name":"Spaghetti","price":14.0,"available":true,"photoUrl":"http://localhost:8080/menu_item_images/restaurant2_Spaghetti.jpg","description":"Delicious Spaghetti","quantity":0},{"name":"Soup","price":15.0,"available":true,"photoUrl":"http://localhost:8080/menu_item_images/restaurant2_Soup.jpg","description":"Delicious Soup","quantity":0}],"totalPrice":75.0,"customerName":"customer20","restaurantName":"restaurant2","status":"Ready For Pickup","customerNote":"","address":"Rothschild St, Rishon LeZion","restaurantAddress":"Allenby St, Ashdod","distance":23.961421335263907,"location":[31.79213,34.64966]}],"preferences":{},"creditCard":{"creditCardNumber":"1234123412341234","expirationDate":"11/11","cvv":"123"},"inAppBalance":0.0,"userName":"customer20","hashedPassword":"5e884898da28047151d0e56f8dc6292773603d0d6aabbdd62a11ef721d1542d8","address":"Rothschild St, Rishon LeZion","phoneNumber":"0508878135","email":"customer20@example.com","location":[31.964752,34.7911272]}