{"orders":[],"menu":[{"name":"Tacos","price":10.0,"available":true,"photoUrl":"menu_item_images/restaurant19_Tacos.jpg","description":"Delicious Tacos","quantity":0},{"name":"Curry","price":11.0,"available":true,"photoUrl":"menu_item_images/restaurant19_Curry.jpg","description":"Delicious Curry","quantity":0},{"name":"Waffles","price":12.0,"available":true,"photoUrl":"menu_item_images/restaurant19_Waffles.jpg","description":"Delicious Waffles","quantity":0},{"name":"Pizza","price":13.0,"available":true,"photoUrl":"menu_item_images/restaurant19_Pizza.jpg","description":"Delicious Pizza","quantity":0},{"name":"BBQ Ribs","price":14.0,"available":true,"photoUrl":"menu_item_images/restaurant19_BBQ Ribs.jpg","description":"Delicious BBQ Ribs","quantity":0},{"name":"Dumplings","price":15.0,"available":true,"photoUrl":"menu_item_images/restaurant19_Dumplings.jpg","description":"Delicious Dumplings","quantity":0}],"businessPhoneNumber":"035562621","cuisine":"Thai","revenue":0.0,"hasProfilePicture":true,"profilePictureUrl":"profile_pictures/restaurant19.jpg","restaurantName":"restaurant19","userName":"restaurant19","hashedPassword":"5e884898da28047151d0e56f8dc6292773603d0d6aabbdd62a11ef721d1542d8","address":"Dizengoff St, Netanya","phoneNumber":"0509791103","email":"restaurant19@example.com","location":[32.3282026,34.8529696]}