{"orders":[],"menu":[{"name":"Pasta","price":10.0,"available":true,"photoUrl":"menu_item_images/restaurant11_Pasta.jpg","description":"Delicious Pasta","quantity":0},{"name":"Spaghetti","price":11.0,"available":true,"photoUrl":"menu_item_images/restaurant11_Spaghetti.jpg","description":"Delicious Spaghetti","quantity":0},{"name":"Ice Cream","price":12.0,"available":true,"photoUrl":"menu_item_images/restaurant11_Ice Cream.jpg","description":"Delicious Ice Cream","quantity":0},{"name":"Dumplings","price":13.0,"available":true,"photoUrl":"menu_item_images/restaurant11_Dumplings.jpg","description":"Delicious Dumplings","quantity":0},{"name":"Risotto","price":14.0,"available":true,"photoUrl":"menu_item_images/restaurant11_Risotto.jpg","description":"Delicious Risotto","quantity":0},{"name":"Nachos","price":15.0,"available":true,"photoUrl":"menu_item_images/restaurant11_Nachos.jpg","description":"Delicious Nachos","quantity":0}],"businessPhoneNumber":"035540966","cuisine":"American","revenue":0.0,"hasProfilePicture":true,"profilePictureUrl":"profile_pictures/restaurant11.jpg","restaurantName":"restaurant11","userName":"restaurant11","hashedPassword":"5e884898da28047151d0e56f8dc6292773603d0d6aabbdd62a11ef721d1542d8","address":"HaShalom St, Holon","phoneNumber":"0508382248","email":"restaurant11@example.com","location":[32.0017708,34.7720435]}